gallery/__init__.py
gallery/admin.py
gallery/apps.py
gallery/locale/fr/LC_MESSAGES/django.mo
gallery/locale/fr/LC_MESSAGES/django.po
gallery/management/__init__.py
gallery/management/commands/__init__.py
gallery/management/commands/scanphotos.py
gallery/migrations/0001_initial.py
gallery/migrations/__init__.py
gallery/models.py
gallery/query count.txt
gallery/resizers/__init__.py
gallery/resizers/pillow.py
gallery/resizers/test_pillow.py
gallery/resizers/test_thumbor.py
gallery/resizers/thumbor.py
gallery/static/css/gallery.css
gallery/storages.py
gallery/templates/admin/gallery/change_list.html
gallery/templates/admin/gallery/scan_photos.html
gallery/templates/admin/gallery/set_access_policy.html
gallery/templates/admin/gallery/unset_access_policy.html
gallery/templates/gallery/album_archive.html
gallery/templates/gallery/album_archive_year.html
gallery/templates/gallery/album_detail.html
gallery/templates/gallery/photo_detail.html
gallery/test_admin.py
gallery/test_models.py
gallery/test_settings.py
gallery/test_storages.py
gallery/test_templates/base.html
gallery/test_urls.py
gallery/test_views.py
gallery/urls.py
gallery/views.py
myks_gallery-0.9.1.dist-info/LICENSE
myks_gallery-0.9.1.dist-info/WHEEL
myks_gallery-0.9.1.dist-info/METADATA
myks_gallery-0.9.1.dist-info/RECORD
