Metadata-Version: 2.1
Name: myks-gallery
Version: 0.9.1
Summary: Photo gallery with granular access control
Home-page: https://github.com/aaugustin/myks-gallery
License: BSD-3-Clause
Author: Aymeric Augustin
Author-email: aymeric.augustin@m4x.org
Requires-Python: >=3.6,<4.0
Classifier: Development Status :: 4 - Beta
Classifier: Environment :: Web Environment
Classifier: Framework :: Django
Classifier: Framework :: Django :: 3.2
Classifier: Framework :: Django :: 4.0
Classifier: Framework :: Django :: 4.1
Classifier: Intended Audience :: Developers
Classifier: License :: OSI Approved :: BSD License
Classifier: Operating System :: OS Independent
Classifier: Programming Language :: Python :: 3
Classifier: Programming Language :: Python :: 3.6
Classifier: Programming Language :: Python :: 3.7
Classifier: Programming Language :: Python :: 3.8
Classifier: Programming Language :: Python :: 3.9
Classifier: Programming Language :: Python :: 3.10
Classifier: Programming Language :: Python :: 3.11
Requires-Dist: django (>=3.2)
Project-URL: Repository, https://github.com/aaugustin/myks-gallery
